twbotlib/__init__.py
twbotlib/base/exceptions.py
twbotlib/base/main.py
twbotlib/base/struct.py
twbotlib-0.0.52.dist-info/METADATA
twbotlib-0.0.52.dist-info/WHEEL
twbotlib-0.0.52.dist-info/top_level.txt
twbotlib-0.0.52.dist-info/RECORD
