Metadata-Version: 2.1
Name: twbotlib
Version: 0.0.52
Summary: 🐦 Unoffical twitch bot library written in Python3 🤖
Home-page: https://github.com/truedl/twbotlib
Author: truedl
Author-email: terajamoffical@example.com
License: UNKNOWN
Platform: UNKNOWN
Classifier: Programming Language :: Python :: 3
Classifier: License :: OSI Approved :: MIT License
Classifier: Operating System :: OS Independent
